lisdf/__init__.py
lisdf/py.typed
lisdf/components/__init__.py
lisdf/components/base.py
lisdf/components/control.py
lisdf/components/gui.py
lisdf/components/material.py
lisdf/components/model.py
lisdf/components/model_mjcf.py
lisdf/components/model_sdf.py
lisdf/components/model_urdf.py
lisdf/components/pddl.py
lisdf/components/scene.py
lisdf/components/sensor.py
lisdf/components/shape.py
lisdf/components/srdf.py
lisdf/components/state.py
lisdf/parsing/__init__.py
lisdf/parsing/all.py
lisdf/parsing/lispddl-builtins.pddl
lisdf/parsing/lispddl-v1.0.grammar
lisdf/parsing/mjcf.py
lisdf/parsing/parse_sdf.py
lisdf/parsing/pddl_j.py
lisdf/parsing/sdf.py
lisdf/parsing/sdf_j.py
lisdf/parsing/srdf.py
lisdf/parsing/string_utils.py
lisdf/parsing/urdf.py
lisdf/parsing/urdf_j.py
lisdf/parsing/xml_j/__init__.py
lisdf/parsing/xml_j/visitor.py
lisdf/parsing/xml_j/xml.py
lisdf/parsing/xml_reflection/__init__.py
lisdf/parsing/xml_reflection/basics.py
lisdf/parsing/xml_reflection/core.py
lisdf/plan_executor/__init__.py
lisdf/plan_executor/executor.py
lisdf/plan_executor/gripper_executor.py
lisdf/plan_executor/interpolator.py
lisdf/plan_executor/joint_space_path_executor.py
lisdf/plan_executor/lisdf_executor.py
lisdf/plan_executor/robots/__init__.py
lisdf/plan_executor/robots/common.py
lisdf/plan_executor/robots/panda.py
lisdf/planner_output/__init__.py
lisdf/planner_output/command.py
lisdf/planner_output/common.py
lisdf/planner_output/config.py
lisdf/planner_output/plan.py
lisdf/utils/__init__.py
lisdf/utils/printing.py
lisdf/utils/transformations.py
lisdf/utils/transformations_more.py
lisdf/utils/typing.py
lisdf-0.1.1.dist-info/METADATA
lisdf-0.1.1.dist-info/WHEEL
lisdf-0.1.1.dist-info/licenses/LICENSE
lisdf-0.1.1.dist-info/RECORD
