Metadata-Version: 2.1
Name: lisdf
Version: 0.1.1
Summary: LISdf - a universal I/O spec for Task and Motion Planning (TAMP).
Project-URL: Homepage, https://github.com/Learning-and-Intelligent-Systems/lisdf/
Author-email: "Learning and Intelligent Systems (MIT CSAIL)" <willshen@mit.edu>
License-Expression: MIT
License-File: LICENSE
Keywords: robotics,sdf,task and motion planning,urdf
Classifier: License :: OSI Approved :: MIT License
Classifier: Programming Language :: Python
Classifier: Programming Language :: Python :: 3.8
Requires-Python: >=3.8
Requires-Dist: lark
Requires-Dist: numpy
Requires-Dist: pyyaml
Provides-Extra: develop
Requires-Dist: black; extra == 'develop'
Requires-Dist: flake8; extra == 'develop'
Requires-Dist: isort; extra == 'develop'
Requires-Dist: mock; extra == 'develop'
Requires-Dist: mypy; extra == 'develop'
Requires-Dist: pytest; extra == 'develop'
Requires-Dist: pytest-cov; extra == 'develop'
Requires-Dist: types-mock; extra == 'develop'
Requires-Dist: types-pyyaml; extra == 'develop'
